selfdb/__init__.py
selfdb/auth.py
selfdb/client.py
selfdb/exceptions.py
selfdb/http_client.py
selfdb/models.py
selfdb/py.typed
selfdb/realtime.py
selfdb/storage.py
selfdb/tables.py
selfdb-0.0.5.dist-info/METADATA
selfdb-0.0.5.dist-info/WHEEL
selfdb-0.0.5.dist-info/RECORD
