Metadata-Version: 2.4
Name: selfdb
Version: 0.0.5
Summary: Python SDK for SelfDB - Full Self-Hosted BaaS Built for AI Agents
Project-URL: Homepage, https://github.com/selfdb/selfdb
Project-URL: Documentation, https://docs.selfdb.io
Project-URL: Repository, https://github.com/selfdb/selfdb
Author: SelfDB Team
License-Expression: MIT
Keywords: api,baas,backend-as-a-service,database,realtime,sdk,selfdb,storage
Classifier: Development Status :: 4 - Beta
Classifier: Framework :: AsyncIO
Classifier: Intended Audience :: Developers
Classifier: License :: OSI Approved :: MIT License
Classifier: Operating System :: OS Independent
Classifier: Programming Language :: Python :: 3
Classifier: Programming Language :: Python :: 3.10
Classifier: Programming Language :: Python :: 3.11
Classifier: Programming Language :: Python :: 3.12
Classifier: Typing :: Typed
Requires-Python: >=3.10
Requires-Dist: httpx>=0.25.0
Requires-Dist: websockets>=12.0
Provides-Extra: dev
Requires-Dist: mypy>=1.0; extra == 'dev'
Requires-Dist: pytest-asyncio>=0.21; extra == 'dev'
Requires-Dist: pytest>=7.0; extra == 'dev'
Requires-Dist: ruff>=0.1; extra == 'dev'
